kitten_box/__init__.py
kitten_box/sample.py
kitten_box/version.py
kitten_box-0.1.7.dist-info/LICENSE.md
kitten_box-0.1.7.dist-info/METADATA
kitten_box-0.1.7.dist-info/WHEEL
kitten_box-0.1.7.dist-info/top_level.txt
kitten_box-0.1.7.dist-info/RECORD
