Metadata-Version: 2.1
Name: kitten-box
Version: 0.1.7
Summary: Simple Py package
Home-page: https://github.com/montionugera/pypi-sample-lib
Author: mont Pasit Nusso
Author-email: montionugera@gmail.com
License: MIT
Keywords: sample
Platform: UNKNOWN
Classifier: Development Status :: 5 - Production/Stable
Classifier: Intended Audience :: Developers
Classifier: Intended Audience :: System Administrators
Classifier: License :: OSI Approved :: MIT License
Classifier: Operating System :: OS Independent
Classifier: Topic :: Software Development :: Libraries :: Python Modules
Classifier: Topic :: Internet
Classifier: Programming Language :: Python :: 3.8
Classifier: Programming Language :: Python :: 3 :: Only
Requires-Python: >=3.8
